Librarymu/__init__.py
Librarymu/golden_ratio.py
golden_info-1.0.dist-info/LICENSE
golden_info-1.0.dist-info/METADATA
golden_info-1.0.dist-info/WHEEL
golden_info-1.0.dist-info/top_level.txt
golden_info-1.0.dist-info/RECORD
